[
  {
    "numberOrder": "",
    "system": "รายละเอียด login",
    "userGroups": "FO",
    "remark": "รายละเอียดสำหรับการ login เข้าสอบ",
    "url": "https://docs.google.com/spreadsheets/d/1pFP7efFgjwtDIlTjEQkUuilkKwrcsGahNYDa4waR1Xs/edit?usp=sharing"
  },
  {
    "numberOrder": "SSS",
    "system": "ระบบประกันสุขภาพ",
    "userGroups": "FO",
    "remark": "Username และ Password ที่เตรียมไว้",
    "url": "https://trnsss.siamsmile.co.th"
  },
  {
    "numberOrder": "PA",
    "system": "ระบบประกันอุบัติเหตุนักเรียน",
    "userGroups": "FO",
    "remark": "Username และ Password ที่เตรียมไว้",
    "url": "https://trnssspa.siamsmile.co.th/"
  },
  {
    "numberOrder": "PA",
    "system": "รายชื่อสำหรับนำเข้า PA นักเรียน",
    "userGroups": "FO",
    "remark": "Username และ Password ที่เตรียมไว้",
    "url": "https://docs.google.com/spreadsheets/d/1aqCcI2sJp41KxMh8bh6JOKtvA8Kag09T/edit?usp=sharing&ouid=101112800460365985196&rtpof=true&sd=truehttps://docs.google.com/spreadsheets/d/1aqCcI2sJp41KxMh8bh6JOKtvA8Kag09T/edit?usp=sharing&ouid=101112800460365985196&rtpof=true&sd=true"
  },
  {
    "numberOrder": "Motor",
    "system": "ระบบประกันรถยนต์",
    "userGroups": "FO",
    "remark": "Username และ Password ที่เตรียมไว้",
    "url": "https://b2b.uat.siamsmile.co.th/"
  },
  {
    "numberOrder": "Claim PH",
    "system": "ระบบเคลม ประกันสุขภาพ",
    "userGroups": "FO",
    "remark": "Username และ Password ที่เตรียมไว้",
    "url": "https://trnsss.siamsmile.co.th"
  },
  {
    "numberOrder": "Claim Online",
    "system": "ระบบสินไหมออนไลน์",
    "userGroups": "FO",
    "remark": "Username และ Password ที่เตรียมไว้",
    "url": "https://trncol.siamsmile.co.th"
  },
  {
    "numberOrder": "เงินสดย่อย",
    "system": "ระบบ เงินสดย่อย",
    "userGroups": "FO",
    "remark": "Username และ Password ที่เตรียมไว้",
    "url": "https://trnpettycash.siamsmile.co.th"
  }
]
